{
  "Data/_ResourcePack.bsa": "6A3B95BB5A710E30",
  "Tools/LipGen/LipGenerator/FonixData.cdf": "E3C25D22A111A139",
  "Data/Dragonborn.esm": "44140CD78C9F2E40",
  "Tools/LipGen/LipGenerator/LipGenerator.exe": "4D1B1925A15A3557",
  "Data/Skyrim - Voices_it0.bsa": "AA963F957AD07185",
  "Data/ccBGSSSE001-Fish.bsa": "B3DA8CE8DE47743E",
  "Data/Skyrim - Textures3.bsa": "7C526C8FDF48569D",
  "Data/Skyrim - Interface.bsa": "04CC995BF4E5C8C9",
  "Data/Skyrim - Voices_de0.bsa": "40082ECC0A9A0690",
  "Skyrim.ccc": "69283889EB935070",
  "Data/Video/BGS_Logo.bik": "7413DEF8BC63A5FF",
  "Skyrim_Default_pl.ini": "F4C741BD57ED5B62",
  "High.ini": "94626AF4EC1B6E07",
  "Data/Skyrim - Animations.bsa": "4BBAB0B96040B37C",
  "Data/Skyrim - Voices_fr0.bsa": "BE5F63DA78109705",
  "bink2w64.dll": "A8A86A1529D67614",
  "Data/Skyrim - Voices_ru0.bsa": "8F3742B138754422",
  "Data/Skyrim - Textures1.bsa": "C6A6F8D194FB1C44",
  "Data/Skyrim - Textures7.bsa": "34FCE2ABF03DAD24",
  "Data/Skyrim - Textures2.bsa": "82BF9B2B597DE374",
  "Data/Skyrim - Textures0.bsa": "CC1C0732532FC3E4",
  "Data/Skyrim - Voices_es0.bsa": "B3B78DD192951CAB",
  "Skyrim_Default_it.ini": "9F933EAB965C33BD",
  "Data/Skyrim - Misc.bsa": "909F0B33FACE261F",
  "Data/MarketplaceTextures.bsa": "5A28356FBC9521A4",
  "SkyrimSE.exe": "69C9237759F21C2E",
  "Skyrim_Default_ja.ini": "3F53DFE0642CEA14",
  "Skyrim_Default_en.ini": "76FCC156B05DE3A5",
  "Data/Update.esm": "EC30AB069B11A0F7",
  "Skyrim_Default_fr.ini": "7D509E4EB17E101B",
  "Skyrim_Default_es.ini": "432FCD7C38928E16",
  "Skyrim_Default_cn.ini": "18B999C9F40DA978",
  "Low.ini": "CAE3FDB9CADCFE26",
  "Skyrim_Default.ini": "76FCC156B05DE3A5",
  "Data/_ResourcePack.esl": "18795EF12611DA1C",
  "Data/ccQDRSSE001-SurvivalMode.esl": "017DB11ED47FED3F",
  "Data/Skyrim - Textures5.bsa": "390F9AD3C332C834",
  "Data/HearthFires.esm": "8FFCB54799EC35F6",
  "Data/Skyrim - Textures6.bsa": "E073161E63316A5A",
  "Data/Skyrim - Voices_en0.bsa": "5AAE4DEF350B7317",
  "Data/Skyrim - Textures4.bsa": "25E7215F0D5F3509",
  "Data/ccBGSSSE001-Fish.esm": "7F9277C101F414D7",
  "Data/Dawnguard.esm": "5FC59A6DF3A7C564",
  "Data/skyrim - voices_ja0.bsa": "AD3E1ABC110C9166",
  "Ultra.ini": "F873DB703DB2EDD1",
  "Tools/RoboVoicer.exe": "8A57A2BDA5AE7301",
  "Data/ccQDRSSE001-SurvivalMode.bsa": "362AC14D5CEF97E6",
  "Medium.ini": "DCE55C6183C7C99F",
  "Galaxy64.dll": "06C5B2069EC2C071",
  "SkyrimSELauncher.exe": "CB98EFFC31C662A5",
  "Skyrim_Default_de.ini": "1C7E3EBF36752F88",
  "Data/Skyrim.esm": "D5366165B226E453",
  "Data/Skyrim - Textures8.bsa": "A031752E3862113F",
  "Tools/LipGen/LipFuzer/LIPFuzer.txt": "279D59843DA9874A",
  "Data/Skyrim - Sounds.bsa": "11FBF7A3687ED6AF",
  "Data/Skyrim - Meshes1.bsa": "06288D2FE22022C8",
  "Data/Skyrim - Meshes0.bsa": "17EB632E9F1F128F",
  "Data/Skyrim - Voices_pl0.bsa": "63B9E8D9BE5A3647",
  "Data/ccBGSSSE025-AdvDSGS.bsa": "2A17047A412FAA32",
  "Tools/LipGen/LipFuzer/LIPFuzer.exe": "EE015151F8D3D5D9",
  "Data/ccBGSSSE037-Curios.esl": "90798A8E09840953",
  "Data/Skyrim - Shaders.bsa": "3F6F890E58A339D3",
  "Data/ccBGSSSE025-AdvDSGS.esm": "5D993C53F1B521D1",
  "Data/ccBGSSSE037-Curios.bsa": "D460DC1DBB4D4C54",
  "SkyrimConsoleDefault.ini": "8EA140699C7F5A9A",
  "Skyrim_Default_ru.ini": "200DF303E7BD63BC"
}